LICENSE
MANIFEST.in
README.rst
setup.cfg
setup.py
aredis/__init__.py
aredis/cache.py
aredis/client.py
aredis/connection.py
aredis/exceptions.py
aredis/lock.py
aredis/nodemanager.py
aredis/pipeline.py
aredis/pool.py
aredis/pubsub.py
aredis/scripting.py
aredis/sentinel.py
aredis/speedups.c
aredis/utils.py
aredis.egg-info/PKG-INFO
aredis.egg-info/SOURCES.txt
aredis.egg-info/dependency_links.txt
aredis.egg-info/requires.txt
aredis.egg-info/top_level.txt
aredis/commands/__init__.py
aredis/commands/cluster.py
aredis/commands/connection.py
aredis/commands/extra.py
aredis/commands/geo.py
aredis/commands/hash.py
aredis/commands/hyperlog.py
aredis/commands/iter.py
aredis/commands/keys.py
aredis/commands/lists.py
aredis/commands/pubsub.py
aredis/commands/scripting.py
aredis/commands/sentinel.py
aredis/commands/server.py
aredis/commands/sets.py
aredis/commands/sorted_set.py
aredis/commands/streams.py
aredis/commands/strings.py
aredis/commands/transaction.py
tests/__init__.py
tests/client/__init__.py
tests/client/conftest.py
tests/client/test_cache.py
tests/client/test_commands.py
tests/client/test_connection.py
tests/client/test_connection_pool.py
tests/client/test_encoding.py
tests/client/test_lock.py
tests/client/test_pipeline.py
tests/client/test_pubsub.py
tests/client/test_scripting.py
tests/client/test_sentinel.py
tests/client/test_streams.py
tests/cluster/__init__.py
tests/cluster/conftest.py
tests/cluster/test_cluster_connection_pool.py
tests/cluster/test_cluster_obj.py
tests/cluster/test_commands.py
tests/cluster/test_lock.py
tests/cluster/test_node_manager.py
tests/cluster/test_pipeline.py
tests/cluster/test_pubsub.py
tests/cluster/test_scripting.py
tests/cluster/test_utils.py