Metadata-Version: 1.2
Name: aredis
Version: 1.1.6
Summary: Python async client for Redis key-value store
Home-page: https://github.com/NoneGG/aredis
Author: Jason Chen
Author-email: 847671011@qq.com
Maintainer: Jason Chen
Maintainer-email: 847671011@qq.com
License: MIT
Keywords: Redis,key-value store,asyncio
Platform: UNKNOWN
Classifier: Development Status :: 5 - Production/Stable
Classifier: Environment :: Console
Classifier: Intended Audience :: Developers
Classifier: License :: OSI Approved :: MIT License
Classifier: Operating System :: OS Independent
Classifier: Programming Language :: Python
Classifier: Programming Language :: Python :: 3.5
Classifier: Programming Language :: Python :: 3.6
Classifier: Programming Language :: Python :: 3.7
Classifier: Programming Language :: Python :: 3.8
